abs_schema_core/__init__.py
abs_schema_core/fields_schema/__init__.py
abs_schema_core/fields_schema/common_schema.py
abs_schema_core/fields_schema/field_schema.py
abs_schema_core/libs/__init__.py
abs_schema_core/libs/extend_enum.py
abs_schema_core/libs/make_optional.py
abs_schema_core-0.1.4.dist-info/METADATA
abs_schema_core-0.1.4.dist-info/WHEEL
abs_schema_core-0.1.4.dist-info/RECORD
