Metadata-Version: 2.4
Name: abs-schema-core
Version: 0.1.4
Summary: AutoBridge Systems Schema Library
Author: AutoBridgeSystems
Author-email: info@autobridgesystems.com
Requires-Python: >=3.11,<4.0
Classifier: Programming Language :: Python :: 3
Classifier: Programming Language :: Python :: 3.11
Classifier: Programming Language :: Python :: 3.12
Classifier: Programming Language :: Python :: 3.13
Classifier: Programming Language :: Python :: 3.14
Requires-Dist: abs-exception-core (>=0.2.0,<0.3.0)
